{
  "Full Name": "Ishan Saraf",
  "Email Address": "sarafi@rose-hulman.edu",
  "Phone Number": "+13125221659",
  "Latest University": "Rose-Hulman Institute of Technology",
  "Degree": "B.S.",
  "Major": "Computer Science",
  "Graduation Date": "February 2020",
  "Previous University": "Dhirubhai Ambani International School",
  "Met on Campus": false,
  "Campus Score": "Not Captured",
  "Cities/States of interest mentioned": [
    "Terre Haute, IN",
    "San Francisco, CA",
    "Mumbai, India"
  ]
}